{
  "database-name": "%%mlFinalDbName%%",
  "range-element-index": [
    {
      "scalar-type": "string",
      "namespace-uri": "",
      "localname": "Education",
      "collation": "http://marklogic.com/collation/codepoint",
      "range-value-positions": false,
      "invalid-values": "reject"
    },
    {
      "scalar-type": "string",
      "namespace-uri": "",
      "localname": "Experience",
      "collation": "http://marklogic.com/collation/codepoint",
      "range-value-positions": false,
      "invalid-values": "reject"
    },
    {
      "scalar-type": "string",
      "namespace-uri": "",
      "localname": "Skill",
      "collation": "http://marklogic.com/collation/codepoint",
      "range-value-positions": false,
      "invalid-values": "reject"
    },
    {
      "scalar-type": "string",
      "namespace-uri": "",
      "localname": "Requirement",
      "collation": "http://marklogic.com/collation/codepoint",
      "range-value-positions": false,
      "invalid-values": "reject"
    }
  ],
  "range-path-index": [
    {
      "scalar-type": "string",
      "collation": "http://marklogic.com/collation/",
      "path-expression": "/matchSummary/URIsToProcess",
      "range-value-positions": true,
      "invalid-values": "reject"
    }
  ]
}
